{
  "type": "object",
  "additionalProperties": false,
  "required": ["items"],
  "properties": {
    "items": {
      "type": "array",
      "items": {
        "type": "object",
        "additionalProperties": false,
        "required": ["newsId", "summaryPoints", "confidence"],
        "properties": {
          "newsId": {"type": "string"},
          "summaryPoints": {
            "type": "array",
            "minItems": 1,
            "maxItems": 2,
            "items": {"type": "string", "maxLength": 140}
          },
          "confidence": {"type": "number", "minimum": 0, "maximum": 1}
        }
      }
    }
  }
}
